LICENSE
MANIFEST.in
README.md
setup.py
bin/detect-requirements
moser_fork_requirements_detector.egg-info/PKG-INFO
moser_fork_requirements_detector.egg-info/SOURCES.txt
moser_fork_requirements_detector.egg-info/dependency_links.txt
moser_fork_requirements_detector.egg-info/requires.txt
moser_fork_requirements_detector.egg-info/top_level.txt
requirements_detector/__compat__.py
requirements_detector/__init__.py
requirements_detector/detect.py
requirements_detector/formatters.py
requirements_detector/requirement.py
requirements_detector/run.py