Metadata-Version: 1.1
Name: moser-fork-requirements-detector
Version: 0.8.1
Summary: Python tool to find and list requirements of a Python project
Home-page: https://github.com/moser/requirements-detector
Author: landscape.io (forked by moser)
Author-email: moser@moserei.de
License: MIT
Keywords: python requirements detector
Platform: UNKNOWN
Classifier: Development Status :: 5 - Production/Stable
Classifier: Environment :: Console
Classifier: Intended Audience :: Developers
Classifier: Operating System :: Unix
Classifier: Topic :: Software Development :: Quality Assurance
Classifier: Programming Language :: Python :: 2.7
Classifier: Programming Language :: Python :: 3.4
Classifier: Programming Language :: Python :: 3.5
Classifier: Programming Language :: Python :: 3.6
Classifier: Programming Language :: Python :: 3.7
Classifier: Programming Language :: Python :: 3.8
Classifier: License :: OSI Approved :: MIT License
